zx81p2wav/__init__.py
zx81p2wav/__main__.py
zx81p2wav/modulator.py
zx81p2wav-0.1.0.dist-info/LICENSE
zx81p2wav-0.1.0.dist-info/METADATA
zx81p2wav-0.1.0.dist-info/WHEEL
zx81p2wav-0.1.0.dist-info/entry_points.txt
zx81p2wav-0.1.0.dist-info/top_level.txt
zx81p2wav-0.1.0.dist-info/RECORD
