Metadata-Version: 2.1
Name: zx81p2wav
Version: 0.1.0
Summary: Minimalistic ZX81 p-file to wav converter
Home-page: https://github.com/themadinventor/zx81p2wav
Author: Fredrik Ahlberg
Author-email: fredrik@z80.se
License: UNKNOWN
Platform: UNKNOWN
